<annotation>
	<folder>images</folder>
	<filename>004898-60.jpg</filename>
	<path>D:\Vida académica\Pós-doc\Projeto\Computador do lab\Source code\yolo4-keras\dataset\images\004898-60.jpg</path>
	<source>
		<database>Unknown</database>
	</source>
	<size>
		<width>480</width>
		<height>640</height>
		<depth>3</depth>
	</size>
	<segmented>0</segmented>
	<object>
		<name>tree</name>
		<pose>Unspecified</pose>
		<truncated>1</truncated>
		<difficult>0</difficult>
		<bndbox>
			<xmin>2</xmin>
			<ymin>1</ymin>
			<xmax>136</xmax>
			<ymax>638</ymax>
		</bndbox>
	</object>
	<object>
		<name>tree</name>
		<pose>Unspecified</pose>
		<truncated>0</truncated>
		<difficult>0</difficult>
		<bndbox>
			<xmin>116</xmin>
			<ymin>4</ymin>
			<xmax>457</xmax>
			<ymax>615</ymax>
		</bndbox>
	</object>
	<object>
		<name>stick</name>
		<pose>Unspecified</pose>
		<truncated>0</truncated>
		<difficult>0</difficult>
		<bndbox>
			<xmin>243</xmin>
			<ymin>517</ymin>
			<xmax>255</xmax>
			<ymax>615</ymax>
		</bndbox>
	</object>
	<object>
		<name>stem</name>
		<pose>Unspecified</pose>
		<truncated>0</truncated>
		<difficult>0</difficult>
		<bndbox>
			<xmin>114</xmin>
			<ymin>534</ymin>
			<xmax>169</xmax>
			<ymax>615</ymax>
		</bndbox>
	</object>
	<object>
		<name>stem</name>
		<pose>Unspecified</pose>
		<truncated>1</truncated>
		<difficult>0</difficult>
		<bndbox>
			<xmin>25</xmin>
			<ymin>523</ymin>
			<xmax>125</xmax>
			<ymax>640</ymax>
		</bndbox>
	</object>
</annotation>
