<annotation>
	<folder>images</folder>
	<filename>044202-16.jpg</filename>
	<path>D:\Vida académica\Pós-doc\Projeto\Computador do lab\Source code\yolo4-keras\dataset\images\044202-16.jpg</path>
	<source>
		<database>Unknown</database>
	</source>
	<size>
		<width>2048</width>
		<height>1536</height>
		<depth>3</depth>
	</size>
	<segmented>0</segmented>
	<object>
		<name>stick</name>
		<pose>Unspecified</pose>
		<truncated>0</truncated>
		<difficult>0</difficult>
		<bndbox>
			<xmin>819</xmin>
			<ymin>913</ymin>
			<xmax>887</xmax>
			<ymax>1422</ymax>
		</bndbox>
	</object>
	<object>
		<name>stem</name>
		<pose>Unspecified</pose>
		<truncated>0</truncated>
		<difficult>0</difficult>
		<bndbox>
			<xmin>915</xmin>
			<ymin>945</ymin>
			<xmax>1049</xmax>
			<ymax>1423</ymax>
		</bndbox>
	</object>
	<object>
		<name>tree</name>
		<pose>Unspecified</pose>
		<truncated>0</truncated>
		<difficult>0</difficult>
		<bndbox>
			<xmin>351</xmin>
			<ymin>143</ymin>
			<xmax>1933</xmax>
			<ymax>1425</ymax>
		</bndbox>
	</object>
</annotation>
