<annotation>
	<folder>images</folder>
	<filename>061123-29.jpg</filename>
	<path>D:\Vida académica\Pós-doc\Projeto\Computador do lab\Source code\yolo4-keras\dataset\images\061123-29.jpg</path>
	<source>
		<database>Unknown</database>
	</source>
	<size>
		<width>480</width>
		<height>640</height>
		<depth>3</depth>
	</size>
	<segmented>0</segmented>
	<object>
		<name>stick</name>
		<pose>Unspecified</pose>
		<truncated>0</truncated>
		<difficult>0</difficult>
		<bndbox>
			<xmin>248</xmin>
			<ymin>465</ymin>
			<xmax>264</xmax>
			<ymax>568</ymax>
		</bndbox>
	</object>
	<object>
		<name>stem</name>
		<pose>Unspecified</pose>
		<truncated>0</truncated>
		<difficult>0</difficult>
		<bndbox>
			<xmin>205</xmin>
			<ymin>426</ymin>
			<xmax>248</xmax>
			<ymax>569</ymax>
		</bndbox>
	</object>
	<object>
		<name>tree</name>
		<pose>Unspecified</pose>
		<truncated>0</truncated>
		<difficult>0</difficult>
		<bndbox>
			<xmin>15</xmin>
			<ymin>107</ymin>
			<xmax>474</xmax>
			<ymax>570</ymax>
		</bndbox>
	</object>
	<object>
		<name>crown</name>
		<pose>Unspecified</pose>
		<truncated>0</truncated>
		<difficult>0</difficult>
		<bndbox>
			<xmin>20</xmin>
			<ymin>110</ymin>
			<xmax>470</xmax>
			<ymax>393</ymax>
		</bndbox>
	</object>
</annotation>
