<annotation>
	<folder>images</folder>
	<filename>151246-10.jpg</filename>
	<path>D:\Vida académica\Pós-doc\Projeto\Computador do lab\Source code\yolo4-keras\dataset\images\151246-10.jpg</path>
	<source>
		<database>Unknown</database>
	</source>
	<size>
		<width>1536</width>
		<height>2048</height>
		<depth>3</depth>
	</size>
	<segmented>0</segmented>
	<object>
		<name>stick</name>
		<pose>Unspecified</pose>
		<truncated>0</truncated>
		<difficult>0</difficult>
		<bndbox>
			<xmin>660</xmin>
			<ymin>1563</ymin>
			<xmax>702</xmax>
			<ymax>1943</ymax>
		</bndbox>
	</object>
	<object>
		<name>stem</name>
		<pose>Unspecified</pose>
		<truncated>0</truncated>
		<difficult>0</difficult>
		<bndbox>
			<xmin>775</xmin>
			<ymin>1634</ymin>
			<xmax>907</xmax>
			<ymax>1932</ymax>
		</bndbox>
	</object>
	<object>
		<name>tree</name>
		<pose>Unspecified</pose>
		<truncated>0</truncated>
		<difficult>0</difficult>
		<bndbox>
			<xmin>78</xmin>
			<ymin>95</ymin>
			<xmax>1341</xmax>
			<ymax>1937</ymax>
		</bndbox>
	</object>
	<object>
		<name>crown</name>
		<pose>Unspecified</pose>
		<truncated>0</truncated>
		<difficult>0</difficult>
		<bndbox>
			<xmin>83</xmin>
			<ymin>100</ymin>
			<xmax>1339</xmax>
			<ymax>1518</ymax>
		</bndbox>
	</object>
	<object>
		<name>tree</name>
		<pose>Unspecified</pose>
		<truncated>0</truncated>
		<difficult>0</difficult>
		<bndbox>
			<xmin>1173</xmin>
			<ymin>876</ymin>
			<xmax>1533</xmax>
			<ymax>1850</ymax>
		</bndbox>
	</object>
	<object>
		<name>crown</name>
		<pose>Unspecified</pose>
		<truncated>0</truncated>
		<difficult>0</difficult>
		<bndbox>
			<xmin>1181</xmin>
			<ymin>884</ymin>
			<xmax>1531</xmax>
			<ymax>1695</ymax>
		</bndbox>
	</object>
</annotation>
