<annotation>
	<folder>new_images</folder>
	<filename>32204-08.jpg</filename>
	<path>D:\Projetos Machine Learning\Python\MobilenetV2-OD\dataset\new_images\32204-08.jpg</path>
	<source>
		<database>Unknown</database>
	</source>
	<size>
		<width>1536</width>
		<height>2048</height>
		<depth>3</depth>
	</size>
	<segmented>0</segmented>
	<object>
		<name>stick</name>
		<pose>Unspecified</pose>
		<truncated>0</truncated>
		<difficult>0</difficult>
		<bndbox>
			<xmin>584</xmin>
			<ymin>1388</ymin>
			<xmax>640</xmax>
			<ymax>1810</ymax>
		</bndbox>
	</object>
	<object>
		<name>stem</name>
		<pose>Unspecified</pose>
		<truncated>0</truncated>
		<difficult>0</difficult>
		<bndbox>
			<xmin>671</xmin>
			<ymin>1482</ymin>
			<xmax>819</xmax>
			<ymax>1822</ymax>
		</bndbox>
	</object>
	<object>
		<name>tree</name>
		<pose>Unspecified</pose>
		<truncated>0</truncated>
		<difficult>0</difficult>
		<bndbox>
			<xmin>3</xmin>
			<ymin>135</ymin>
			<xmax>1524</xmax>
			<ymax>1825</ymax>
		</bndbox>
	</object>
	<object>
		<name>crown</name>
		<pose>Unspecified</pose>
		<truncated>0</truncated>
		<difficult>0</difficult>
		<bndbox>
			<xmin>16</xmin>
			<ymin>138</ymin>
			<xmax>1521</xmax>
			<ymax>1459</ymax>
		</bndbox>
	</object>
</annotation>
